LICENSE.txt
MANIFEST.in
README.rst
requirements.txt
setup.py
test-requirements.txt
versioncheck/__init__.py
versioncheck/check.py
versioncheck/exceptions.py
versioncheck.egg-info/PKG-INFO
versioncheck.egg-info/SOURCES.txt
versioncheck.egg-info/dependency_links.txt
versioncheck.egg-info/requires.txt
versioncheck.egg-info/top_level.txt