Metadata-Version: 1.1
Name: versioncheck
Version: 0.0.1
Summary: Version check decorator
Home-page: UNKNOWN
Author: Tina Tang
Author-email: tina.tang@emc.com
License: Apache Software License
Keywords: version checker
Platform: any
Classifier: Programming Language :: Python
Classifier: Programming Language :: Python :: 2.7
Classifier: Programming Language :: Python :: 3.4
Classifier: Programming Language :: Python :: 3.5
Classifier: Programming Language :: Python :: 3.6
Classifier: Natural Language :: English
Classifier: Intended Audience :: Developers
Classifier: Operating System :: OS Independent
Classifier: Development Status :: 4 - Beta
Classifier: Topic :: Utilities
Classifier: License :: OSI Approved :: Apache Software License
